chemyst/PVnRT.py
chemyst/__init__.py
chemyst/conversions.py
chemyst/gas_laws.py
chemyst/molar.py
chemyst/moles_mass.py
chemyst/yields.py
chemyst-2.3.0.dist-info/LICENSE
chemyst-2.3.0.dist-info/METADATA
chemyst-2.3.0.dist-info/WHEEL
chemyst-2.3.0.dist-info/top_level.txt
chemyst-2.3.0.dist-info/RECORD
