Metadata-Version: 2.1
Name: chemyst
Version: 2.3.0
Summary: Useful functions to work with basic chemistry and stochiemetry
Home-page: https://github.com/mordy-python/chemyst
Author: Mordy Waldo
Author-email: imky171@gmail.com
License: MIT
Download-URL: https://pypi.org/project/chemyst/
Keywords: Chemistry,Chem,Periodic table
Platform: UNKNOWN
